odoo/addons/coupon_portal_commercial_partner_applicability/README.rst
odoo/addons/coupon_portal_commercial_partner_applicability/__init__.py
odoo/addons/coupon_portal_commercial_partner_applicability/__manifest__.py
odoo/addons/coupon_portal_commercial_partner_applicability/controllers/__init__.py
odoo/addons/coupon_portal_commercial_partner_applicability/controllers/portal.py
odoo/addons/coupon_portal_commercial_partner_applicability/i18n/coupon_portal_commercial_partner_applicability.pot
odoo/addons/coupon_portal_commercial_partner_applicability/readme/CONFIGURE.rst
odoo/addons/coupon_portal_commercial_partner_applicability/readme/CONTRIBUTORS.rst
odoo/addons/coupon_portal_commercial_partner_applicability/readme/DESCRIPTION.rst
odoo/addons/coupon_portal_commercial_partner_applicability/readme/USAGE.rst
odoo/addons/coupon_portal_commercial_partner_applicability/static/description/icon.png
odoo/addons/coupon_portal_commercial_partner_applicability/static/description/index.html
odoo_addon_coupon_portal_commercial_partner_applicability-15.0.1.0.0.4.dist-info/METADATA
odoo_addon_coupon_portal_commercial_partner_applicability-15.0.1.0.0.4.dist-info/WHEEL
odoo_addon_coupon_portal_commercial_partner_applicability-15.0.1.0.0.4.dist-info/top_level.txt
odoo_addon_coupon_portal_commercial_partner_applicability-15.0.1.0.0.4.dist-info/RECORD
