Metadata-Version: 2.1
Name: odoo-addon-coupon-portal-commercial-partner-applicability
Version: 15.0.1.0.0.4
Summary: Add possibility to see your company coupons on portal
Home-page: https://github.com/OCA/sale-promotion
Author: Tecnativa, Odoo Community Association (OCA)
Author-email: support@odoo-community.org
License: AGPL-3
Platform: UNKNOWN
Classifier: Programming Language :: Python
Classifier: Framework :: Odoo
Classifier: Framework :: Odoo :: 15.0
Classifier: License :: OSI Approved :: GNU Affero General Public License v3
Classifier: Development Status :: 4 - Beta
Requires-Python: >=3.8
Requires-Dist: odoo-addon-coupon-commercial-partner-applicability <15.1dev,>=15.0dev
Requires-Dist: odoo-addon-coupon-portal <15.1dev,>=15.0dev
Requires-Dist: odoo <15.1dev,>=15.0a
